Metadata-Version: 2.4
Name: dycw-ibapi
Version: 1.0.3
Requires-Python: >=3.12
